AUTHORS.rst
CONTRIBUTING.rst
LICENSE
MANIFEST.in
README.rst
getchangeset
setup.cfg
setup.py
docs/Makefile
docs/authors.rst
docs/contributing.rst
docs/index.rst
docs/installation.rst
docs/readme.rst
docs/usage.rst
jujubundlelib/__init__.py
jujubundlelib/changeset.py
jujubundlelib/cli.py
jujubundlelib/models.py
jujubundlelib/pyutils.py
jujubundlelib/references.py
jujubundlelib/typeutils.py
jujubundlelib/utils.py
jujubundlelib/validation.py
jujubundlelib.egg-info/PKG-INFO
jujubundlelib.egg-info/SOURCES.txt
jujubundlelib.egg-info/dependency_links.txt
jujubundlelib.egg-info/not-zip-safe
jujubundlelib.egg-info/requires.txt
jujubundlelib.egg-info/top_level.txt
jujubundlelib/tests/__init__.py
jujubundlelib/tests/helpers.py
jujubundlelib/tests/test_changeset.py
jujubundlelib/tests/test_cli.py
jujubundlelib/tests/test_integration.py
jujubundlelib/tests/test_models.py
jujubundlelib/tests/test_pyutils.py
jujubundlelib/tests/test_references.py
jujubundlelib/tests/test_typeutils.py
jujubundlelib/tests/test_utils.py
jujubundlelib/tests/test_validation.py